eryx/__init__.py
eryx/_eryx.abi3.so
eryx/_eryx.pyi
eryx/py.typed
pyeryx-0.2.1.dist-info/METADATA
pyeryx-0.2.1.dist-info/WHEEL
pyeryx-0.2.1.dist-info/RECORD
