Metadata-Version: 2.4
Name: pyeryx
Version: 0.2.1
Classifier: Development Status :: 3 - Alpha
Classifier: Intended Audience :: Developers
Classifier: License :: OSI Approved :: MIT License
Classifier: License :: OSI Approved :: Apache Software License
Classifier: Programming Language :: Python :: 3
Classifier: Programming Language :: Python :: 3.9
Classifier: Programming Language :: Python :: 3.10
Classifier: Programming Language :: Python :: 3.11
Classifier: Programming Language :: Python :: 3.12
Classifier: Programming Language :: Python :: 3.13
Classifier: Programming Language :: Rust
Classifier: Topic :: Security
Classifier: Topic :: Software Development :: Interpreters
Requires-Dist: pytest ; extra == 'dev'
Requires-Dist: pytest-asyncio ; extra == 'dev'
Requires-Dist: mypy ; extra == 'dev'
Requires-Dist: requests ; extra == 'dev'
Requires-Dist: httpx ; extra == 'dev'
Provides-Extra: dev
Summary: Python sandbox powered by WebAssembly
Keywords: sandbox,wasm,webassembly,security,isolation
License: MIT OR Apache-2.0
Requires-Python: >=3.9
